<?xml version="1.0" encoding="UTF-8"?><typeSystemDescription xmlns="http://uima.apache.org/resourceSpecifier">
  <name>NamedEntity</name>
  <description/>
  <version>1.0</version>
  <vendor/>
  <types>
    <typeDescription>
      <name>edu.cmu.lti.type.NamedEntity</name>
      <description/>
      <supertypeName>uima.tcas.Annotation</supertypeName>
      <features>
        <featureDescription>
          <name>NamedEntityType</name>
          <description>Stores the Named Entity type eg. GENE</description>
          <rangeTypeName>uima.cas.String</rangeTypeName>
        </featureDescription>
        <featureDescription>
          <name>SourceID</name>
          <description>Stores the source document ID from where the Named Entity was extracted</description>
          <rangeTypeName>uima.cas.String</rangeTypeName>
        </featureDescription>
        <featureDescription>
          <name>NamedEntityMention</name>
          <description>Stores the Named Entity mention in the given text</description>
          <rangeTypeName>uima.cas.String</rangeTypeName>
        </featureDescription>
      </features>
    </typeDescription>
  </types>
</typeSystemDescription>
